linlangleyprime-0.7.data/scripts/generator
primepackage/__init__.py
primepackage/primeio.py
primepackage/primemodule.py
linlangleyprime-0.7.dist-info/LICENSE
linlangleyprime-0.7.dist-info/METADATA
linlangleyprime-0.7.dist-info/WHEEL
linlangleyprime-0.7.dist-info/top_level.txt
linlangleyprime-0.7.dist-info/RECORD
